preceptron/__init__.py
preceptron/perceptron.py
Perceptron_Pacakge_thangarajdeivasikamani-0.0.1.dist-info/LICENSE
Perceptron_Pacakge_thangarajdeivasikamani-0.0.1.dist-info/METADATA
Perceptron_Pacakge_thangarajdeivasikamani-0.0.1.dist-info/WHEEL
Perceptron_Pacakge_thangarajdeivasikamani-0.0.1.dist-info/top_level.txt
Perceptron_Pacakge_thangarajdeivasikamani-0.0.1.dist-info/RECORD
