Metadata-Version: 2.1
Name: Perceptron-Pacakge-thangarajdeivasikamani
Version: 0.0.1
Summary: its an implimentation of Perceptron
Home-page: https://github.com/thangarajdeivasikamani/Perceptron Pacakge
Author: thangarajdeivasikamani
Author-email: Thangarajerode@gmail.com
License: UNKNOWN
Project-URL: Bug Tracker, https://github.com/thangarajdeivasikamani/Perceptron Pacakge/issues
Platform: UNKNOWN
Classifier: Programming Language :: Python :: 3
Classifier: License :: OSI Approved :: MIT License
Classifier: Operating System :: OS Independent
Requires-Python: >=3.7
License-File: LICENSE
Requires-Dist: numpy
Requires-Dist: tqdm
